wordutilities/__init__.py
wordutilities/__main__.py
wordutilities/wordutilities.py
wordutilities/words/words.py
wordutilities/words/words_alpha.txt
wordutilities/words/words_dict.json
wordutilities-0.1.5.dist-info/LICENSE
wordutilities-0.1.5.dist-info/METADATA
wordutilities-0.1.5.dist-info/WHEEL
wordutilities-0.1.5.dist-info/entry_points.txt
wordutilities-0.1.5.dist-info/top_level.txt
wordutilities-0.1.5.dist-info/RECORD
