Metadata-Version: 2.1
Name: wordutilities
Version: 0.1.5
Summary: A package that provides some small tools for English words.
Author-email: Stella Zhang <syz248@nyu.edu>, Focspam <focspam@gmail.com>, Jakob Hablitz <jsh9965@nyu.edu>, Josckar Palomeque-Elias <jp5936@nyu.edu>
License: GNU GENERAL PUBLIC LICENSE
Project-URL: Homepage, https://github.com/software-students-spring2024/3-python-package-exercise-snailman
Project-URL: Repository, https://github.com/software-students-spring2024/3-python-package-exercise-snailman.git
Project-URL: Bug Tracker, https://github.com/software-students-spring2024/3-python-package-exercise-snailman/issues
Keywords: python,package,build,words
Classifier: Programming Language :: Python :: 3
Classifier: Intended Audience :: Education
Classifier: License :: OSI Approved :: GNU General Public License v3 (GPLv3)
Classifier: Operating System :: OS Independent
Requires-Python: >=3.7
License-File: LICENSE
Provides-Extra: dev
Requires-Dist: pytest ; extra == 'dev'
